ansible_scaffold.py
ansible_scaffold-1.0.0.dist-info/METADATA
ansible_scaffold-1.0.0.dist-info/WHEEL
ansible_scaffold-1.0.0.dist-info/entry_points.txt
ansible_scaffold-1.0.0.dist-info/top_level.txt
ansible_scaffold-1.0.0.dist-info/RECORD
