Metadata-Version: 2.4
Name: ansible-scaffold
Version: 1.0.0
Summary: Create a clean starter Ansible scaffold structure quickly.
Author: Dayton Jones
License-Expression: MIT
Project-URL: Homepage, https://github.com/daytonjones/ansible-scaffold
Project-URL: Source, https://github.com/daytonjones/ansible-scaffold
Project-URL: Tracker, https://github.com/daytonjones/ansible-scaffold/issues
Keywords: ansible,ansible-playbook,ansible-roles,devops,automation,cli-tool,python3
Classifier: Programming Language :: Python :: 3
Classifier: Operating System :: OS Independent
Classifier: Topic :: System :: Systems Administration
Classifier: Topic :: Utilities
Requires-Python: >=3.9
Requires-Dist: colorama
